{
    "title": "Los costarricenses debemos alzarnos en armas… contra el dengue - Costa Rica Azul",
    "slug": "dengue-costa-rica",
    "type": "blog",
    "categories": "Sin categoría",
    "author": "Sin autor",
    "date": "Sin fecha",
    "content": "Los costarricenses debemos alzarnos en armas… contra el dengue\nCon cierta frecuencia recibimos comentarios en nuestros canales sociales sobre un “inminente” conflicto bélico relacionado con las controversias de la frontera norte. Desde nuestra perspectiva estos asuntos se deben dirimir mediante el Derecho Internacional, como se está haciendo actualmente.\nPero, sin darnos cuenta, hemos sido invadidos y colonizados por el mosquito aedes aegypti que transmite el dengue y, dada la tasa de contagios, es posible que este sea el año con más enfermos diagnosticados con ese mal en la historia del país.\nSomos un país sin ejército, que a diferencia de otras naciones, invierte su presupuesto en salud y educación. Sin embargo, esta guerra no se gana si el pueblo no toma las armas. Estamos perdiendo la batallas y esto no cambiará salvo que un ejército civil salga de la trinchera a eliminar los criaderos, usar repelente, colocar cedazos en puertas y ventanas y usar toldo a la hora de dormir.\n“Las comunidades exigen fumigaciones por parte del equipo de control de vectores, sin entender que esta es una medida poco eficaz, ya que lo más importante es actuar contra las larvas para que las mismas no se desarrollen, y esto se logra destruyendo criaderos, aplicando abate y otros controles biológicos”, señala la bloguera, médica infectóloga y exministra de Salud María Luisa Ávila.\nEl costo del dengue para el país no ha sido cuantificado y supera en mucho los días de incapacidad, con decenas de miles de días laborales perdidos, ausencias a clases, etc., e implica un serio costo financiero para la Seguridad Social, que tiene salas de espera, consultas y salones llenos de enfermos de un mal que se puede prevenir..\nSi no actuamos pronto veremos el efecto económico en el turismo, con alertas de las embajadas, noticias internacionales y la misma referencia en redes sociales de quienes nos visitaron, alertando a otros de que adquirió dengue después en su paseo por nuestro paraíso.\nHemos logrado mantener nuestra nación como un faro de luz internacional, sin padecer conflictos fratricidas, dictaduras y opresión a los Derechos Humanos, pero no estamos protegiendo a nuestra niñez y adulto mayor de la munición que yace en los criaderos del mosquito.\nComo señala la doctora Ávila, esto se resuelve actuando en entorno inmediato “el dengue requiere el concurso de muchas instituciones, con la participación de diversos actores sociales. Controlar el dengue es costoso y requiere fuerte inversión económica. La luz de esperanza al final del túnel, es la vacuna, la cual es posible que tarde dos años más en comercializarse. Mientras tanto, actuemos en nuestro entorno laboral y familiar manteniéndolos libres de criaderos, fomentando ambientes saludables”.\nEnlístece y salga a combatir. Enrole a sus vecinos, miembros de su iglesia, compañeros de estudio y trabajo. Salgamos de la trinchera y dobleguemos a este enemigo. Expulsémoslo del territorio nacional.\nReinventemos el futuro de Costa Rica; un futuro próspero, libre de dengue.\nTags :\nadultos mayores\nccss\ncosta rica\ndengue\nsalud\nseguridad social\nturismo\nRelated Posts\nNo Image\n¡Un nuevo Limón!\nNo Image\nEs hora de reactivar la economía guanacasteca\nNo Image\nNicoya: paraíso mundial para el retiro\nNo Image\nCosta Rica como destino mundial “gluten free”\nNo Image\nTurismo azul: oportunidades y retos\nNo Image\nMitos del turismo de salud y bienestar\nSin comentarios\nLeave a Comment\nCancel reply\nYour email address will not be published.\nGuardar mi nombre, correo electrónico y sitio web en este navegador para la próxima vez que haga un comentario."
}