{
    "title": "Nuevo libro brinda consejos prácticos para un mejor envejecimiento - Costa Rica Azul",
    "slug": "nuevo-libro-brinda-consejos-practicos-mejor-envejecimiento",
    "type": "blog",
    "categories": "Sin categoría",
    "author": "Sin autor",
    "date": "Sin fecha",
    "content": "Nuevo libro brinda consejos prácticos para un mejor envejecimiento\n¿Cómo se debe abordar la depresión, qué ejercicios se deben realizar para la controlar la incontinencia urinaria, cuáles son los beneficios de la espiritualidad, qué acciones se deben tomar para reducir el impacto de las caídas en la población adulta mayo?\nEstos consejos y otros están incluidos en el libro: “\nEl arte de envejecer bien, consejos prácticos\n” que lanzó esta semana el Hospital Nacional de Geriatría y Gerontología (HNGG).\nEl libro sale a luz bajo el sello de la Editorial Nacional de Salud y Seguridad Social (Ednasss) de la Caja Costarricense de Seguro Social (CCSS) y contó con el apoyo logístico de la Fundación Costarricense para la Investigación y Docencia en Geriatría y Gerontología (Fundogen).\nSegún lo explicó el director del centro médico, el\ndoctor Fernando Morales Martínez\n, la publicación tiene como objetivo convertirse en un instrumento para mejorar la calidad de vida de la población adulta mayor, pues en la obra se incluye una gama de consejos prácticos ofrecidos por especialistas en diversas disciplinas de las ciencias de la salud y de las ciencias sociales.\nDe acuerdo con el especialista, se aprovecha la experiencia y los conocimientos adquiridos por 30 especialistas que laboran en el Hospital Nacional de Geriatría y Gerontología para ponerla al servicio de la población costarricense.\nLos consejos son variados y están relacionados con los temas más recurrentes que se abordan tanto en el hospital geriátrico, como en otros establecimientos de salud, ubicados en diferentes puntos del territorio nacional.\nDurante la presentación, la representante de la Organización Panamericana de la Salud (OPS) en Costa Rica, la\ndoctora Lillian Reneau Vernon\n, destacó la importancia que el nuevo texto tendrá para las personas mayores, sus familiares y cuidadores.\n“El término envejecimiento saludable se ha utilizado para referirse a un estado positivo y libre de enfermedades. Sin embargo, con el envejecimiento, la mayoría de los problemas de salud son el resultado, no sólo de la presencia de enfermedades crónicas que coexisten en un mismo sujeto, sino de la interacción de las mismas con el propio proceso de envejecimiento, y dicha interacción genera como resultado una modificación en la capacidad funcional que finalmente repercute en sus hábitos de vida”, explicó Reneau.\nLa representante de la OPS agregó que,\n“el concepto de envejecimiento saludable se entiende como el proceso de fomentar y mantener la capacidad funcional que permite el bienestar en la vejez. Con este nuevo concepto, envejecer de manera saludable no significa envejecer sin enfermedades. Envejecer de manera saludable significa ser capaz de hacer durante el máximo tiempo posible las cosas a las que damos valor. Para lograr esto, el rol de los estilos de vida, el apoyo de la familia, las redes sociales y los cuidadores de las personas mayores es fundamental”.\nEl arte de envejecer bien: consejos prácticos\n, constituye una respuesta a un clamor de los pacientes  y parientes que acuden a la\nEscuela de Oro\nque realiza el HNGG, quienes solicitaron tener una guía que les permitiera cuidar su salud en forma integral y que fortaleciera las recomendaciones ofrecidas en esa ventana educativa que abrió el hospital hace 17 años.\nEl libro contiene consejos muy prácticos que los pacientes pueden seguir en los distintos escenarios donde se desarrollan prevenir, retrasar o controlar algunos problemas que deterioran sus condiciones de salud.\nAlgunos de los temas que se abordan en esta publicación son las siguientes:\nImportancia de la salud oral.\nCuáles son y para qué sirven los exámenes de laboratorio.\nLa vacunación en el adulto mayor.\nCuidados Paliativos.\nAbordaje de la fase terminal y el duelo.\nEstreñimiento.\nEjercicios para estimular la memoria.\nCómo prevenir y curar úlceras por presión.\nPérdidas del apetito.\nRecomendaciones nutricionales.\nCataratas.\nManejo del trastorno del sueño.\nDepresión y ansiedad.\nEmergencias abdominales\nEnfermedades de la próstata.\nManejo de los medicamentos.\nDificultades para deglutir.\nEl libro tiene un costo de ¢5000 y está a disposición del público en las instalaciones del HNGG.\nTodas las personas merecen un envejecimiento saludable y digno.\n¡Reinventemos el futuro!\nTags :\nadultos mayores\nconsejos prácticos\ncosta rica azul\nEl arte de envejecer bien\nEscuela de Oro\nHospital Nacional de Geriatría y Gerontología\nLibro\nReinventemos el futuro\nRelated Posts\nNo Image\nCosta Rica es de los países más amistosos del mundo ¿Qué hacemos?\nNo Image\nVivimos en el país más feliz de latinoamérica ¿Qué hacemos?\nNo Image\nCosta Rica da pequeño pero importante paso en turismo de bienestar\nNo Image\nPanamá es elegido como el mejor destino para retirados en Centro América\nNo Image\nLos costarricenses debemos alzarnos en armas… contra el dengue\nNo Image\nLa integración del adulto mayor como motor del modelo de desarrollo nacional\nSin comentarios\nLeave a Comment\nCancel reply\nYour email address will not be published.\nGuardar mi nombre, correo electrónico y sitio web en este navegador para la próxima vez que haga un comentario."
}