{
    "title": "UNA | Costa Rica Azul : Blog",
    "slug": "una",
    "type": "blog",
    "categories": "Interés General",
    "author": "crazul",
    "date": "10 octubre, 2013",
    "content": "El doctor Christian Rivera; coordinador de Costa Rica Azul, el fotoperiodista bachiller Jimmy Córdoba y el licenciado José A. Medrano; fundador de Ticoblogger fueron los conferencistas invitados del evento “Una mirada a las redes sociales, el emprendimiento social y la fotografía” en la Universidad Nacional. En su ponencia Rivera explicó el nuevo paradigma educativo de […]"
}