{
    "title": "Nuevos rankings ¿Dónde están las universidades costarricenses? | Costa Rica Azul : Blog",
    "slug": "universidades-costa-rica",
    "type": "blog",
    "content": "Los rankings universitarios “miden, entre otras cosas, la reputación de cada universidad en círculos académicos internacionales, el porcentaje de profesores con doctorados, y sus logros en investigación científica”, vía Oppenheimera.\nEstas clasificaciones sirven para orientar al mundo sobre cuáles son las naciones y casas de enseñanza que pueden formar mejor a un estudiante.\nEl entorno internacional cambia y el mundo se hace cada vez más pequeño, superando los estándares locales y regionales, entrando en un intercambio global, donde las naciones con esfuerzos ordenados y concatenados por una economía del conocimiento tienen mayores probabilidades de éxito para generar riqueza, que beneficie la recaudación fiscal, produzca movilidad social, cree\nemprendimientos\ny empleos de mejor calidad que los anteriormente disponibles.\nEn el nuevo Ranking Académico de Universidades del Mundo 2013 de la Universidad Jiao Tong de Shanghai, y el Ranking QS de Universidades del Mundo 2013, no aparece ninguna universidad latinoamericana entre las primeras 100, lo cual lesiona la imagen de la región para inversión de alto valor agregado y destino académico.\nSegún la investigación del columnista, una de las razones por las cuales la región se ha quedado rezagada es en el poco dominio del inglés como lengua vehicular, lo cual en nuestro país ha tenido tímidos esfuerzos de solución.\nEs difícil de comprender cómo una persona hace un curso de inglés en una institución privada y llega a tener un dominio apropiado de la lengua, mientras que durante los cinco años de secundaria pública apenas logra manejar unas frases básicas que no le permiten pensar y comunicarse en dicha lengua.\nMientras algunos quisieran homologar hacia abajo, poniendo trabas a las escuelas y colegios privados que sí son exitosos enseñando esta y otras lenguas, lo que debemos hacer es importar su metodología a la\neducación pública\n, homologando hacia arriba.\nDe igual forma es urgente ampliar el espectro académico de calidad orientado a la ciencia, matemática, ingeniería, la investigación aplicada y la generación de patentes; ya que hemos sido exitosos enseñando letras, pero apenas un pequeño porcentaje elige carreras numéricas. Además es imperativo que se tenga como norte el engranaje estratégico e innovador: universidad, industria-comercio y comunidad, pues el divorcio entre las casas de enseñanza y las necesidades de la sociedad es evidente ante el hecho que nuestros universitarios no se colocan laboralmente en los campos para los cuales se prepararon, ni con las remuneraciones esperadas, esto en detrimento de la retribución al Estado, los ciudadanos que contribuyeron con su formación y el crecimiento económico de la nación, pero más importante con su realización como ciudadanos exitosos.\nAdemás, es hora de formar\nemprendedores criollos\n, nuestros propios semilleros de nuevas empresas, para superar el ideal de vida como empleado público o de tecnomaquila y empezar a crear una clase empresarial de clase media basada en el mérito y la economía del conocimiento, no en el apellido.\nAlgunas personas repelen estas propuestas argumentando que “la educación no debe tener sentido económico”, lo cual rechazamos, ya que un pueblo donde la riqueza y el conocimiento no van de la mano está condenado a la pobreza perpetua.\nEl conocimiento sin resultado económico no florece, afecta a la sociedad y nos ancla más en el subdesarrollo. Debemos comprender la dura realidad de que los rankings locales y centroamericanos carecen de impacto en el escenario económico internacional. Es hora de dejar de compararnos con el vecindario y dar la batalla para que nuestras universidades\nexporten e importen conocimiento\n.\nLeer\nLos nuevos rankings universitarios.\nCompártelo:\nFacebook\nGoogle +1\nLinkedIn\nTwitter",
    "tags": []
}