{
    "title": "Encuentro comunal por la salud - Costa Rica Azul",
    "slug": "coopevega-la-fortuna-san-carlos",
    "type": "blog",
    "content": "Encuentro comunal por la salud\nInterés General\n,\nTurismo de Salud y Bienestar\nUno de los pilares de una sociedad propositiva es la solidaridad y acción social para el desarrollo comunal, valores que promovemos en Costa Rica Azul.\nComo parte de esta motivación participamos el sábado 13 de abril en la “\nFeria de Salud\n” en Coopevega de Cutris de San Carlos, organizada en conjunto con la Iglesia H.O.R.E.D, de Ciudad Quesada.\nNiños, adultos y ancianos fueron recibidos en las instalaciones de la escuela local, donde los miembros de la congregación compartieron música en vivo y mensajes positivos, mientras el equipo médico brindó atención gratuita en\nodontología\n, medicina general, dermatología, farmacia y cirugía plástica.\nSe brindaron servicios de salud a una gran cantidad de personas, una de ellos fue la señora María Fajardo, vecina de un caserío alejado del centro de Coopevega, a quién se le realizó una intervención menor en un pie, ella felicitó a la Congregación, a la Asociación de Desarrollo y al equipo médico de Costa Rica Azul “me parece excelente que vengan aquí tan largo a hacer estos trabajos, les damos gracias a Dios, ojalá vuelvan a venir, tengo vecinos que aprovecharon para arrancarse una muela o hacer consultas”.\nPara el doctor Howard Rojas, coordinador de los galenos, “más y más personas pueden arrollarse las mangas y de forma sencilla, sin un gran esfuerzo, brindar ayuda y capacitación”.\nCatalina Mendieta se encargó de coordinar la logística en los consultorios, organizar a los pacientes y velar por los insumos necesarios en la atención e intervenciones “estamos demostrando que la unión hace la fuerza, diferentes sectores nos hemos organizado para compartir en una bella comunidad y disfrutar de un día de excelentes resultados”, señaló.\nEl Dr. Christian Rivera, coordinador de Costa Rica Azul, manifestó que la labor realizada supera en mucho una respuesta en salud “nuestra riqueza humana es encontrarnos, escuchar y compartir esperanza, todos los costarricenses, sin importar a qué actividad nos dediquemos, podemos incorporarnos a actividades solidarias y retribuir a la sociedad, no se trata de regalar sino de transformar, todos tenemos que ponernos la camiseta y actuar”.\nNuestra iniciativa agradece al pastor Reinaldo Quirós, de la Iglesia Hored, por la coordinación y realización de los trámites respectivos para que la actividad contara con todos los permisos, al señor Uriel Sánchez, del Ministerio de Salud de Coopevega, por el control, apoyo y facilidades brindadas, así como a los señores Francisco Alfaro y Randall Azofeifa de la Asociación de Desarrollo por promover la feria y que la experiencia fuera aprovechada por todos los vecinos.\nLos servicios de salud fueron brindados por los doctores Julio Rojas (medicina general y dermatología), Howard Rojas (medicina general y farmacia), Wendy Fonseca (odontología),  Ana Gabriela Vega Corea (ortodoncista orthokinética), Erick Rivera (odontología y cirugía maxilofacial) y Christian Rivera (cirujano plástico).\nCosta Rica Azul\nes una organización sin vínculo político o religioso, que busca revitalizar la economía nacional, crear y fortalecer microempresas, promover la\neducación\nen todos los niveles y propiciar una cultura de emprendimiento, teniendo como eje una nueva visión del sector turístico, integrado al concepto de\nsalud y bienestar\npara todos, y más allá de las palabras con acciones.\nVer fotos de la feria\nTags :\ncoopevega\ncosta rica\ndesarrollo\nOportunidad\nsalud\nsan carlos",
    "tags": [
        "coopevega",
        "costa rica",
        "desarrollo",
        "Oportunidad",
        "salud",
        "san carlos"
    ]
}