{
    "title": "Hábitos saludables y espiritualidad son los secretos para vivir más de los nicoyanos - Costa Rica Azul",
    "slug": "habitos-saludables-espiritualidad-los-secretos-vivir-los-nicoyanos",
    "type": "blog",
    "content": "Hábitos saludables y espiritualidad son los secretos para vivir más de los nicoyanos\nSalud y Bienestar\nUna elevada dosis de espiritualidad, actividad física constante, pocos medicamentos, una dieta basada en leguminosas, aves y animales de corral y cuajada…son las principales razones que, de acuerdo con especialistas del Hospital Nacional de Geriatría y Gerontología, explican la longevidad de 43 centenarios que residen en una de las cincos Zonas Azules del mundo y que se localiza en Costa Rica: la península de Nicoya.\nLos hallazgos fueron revelados, hoy, por el equipo de geriatras que intervino en el estudio y que implicó una batería de cerca de 50 pruebas diferentes para conocer el perfil clínico, funcional, psíquico y social de estas personas que superaron los 100 años de edad.\nDe acuerdo con el doctor Fernando Morales Martínez, director del Hospital Nacional de Geriatría y Gerontología, la investigación siguió todos los requerimientos bioéticos que exige la Caja Costarricense de Seguro Social (CCSS) y el Ministerio de Salud para la realización de investigaciones de esta envergadura y que implicó exámenes de laboratorio, electrocardiogramas, pruebas cognitivas, de la marcha y otros test, las que, en su conjunto, permitieron explicar el porqué de su longevidad.\nEl estudio se efectuó en la península de Nicoya por ser considerada una “Zona Azul” en el mundo, ya que posee un área específica de alta prevalencia de centenarios y que se caracteriza por un estilo de vida y un entorno determinado. En Costa Rica, en el momento de la investigación, la proporción de centenarios por habitante era de uno por cada 7 941 habitante y en la Península de Nicoya ( Nandayure, Carrillo, Hojancha, Santa Cruz y Nicoya) fue de un centenario por cada 4 257 habitantes.\nPrincipales Hallazgos del Estudio.\nSe analizaron 43 centenarios, cuya edad media fue de 101 años, de los cuales 18 eran hombres y 25 eran mujeres, la mayoría vive en Santa Cruz, predomina la viudez en las mujeres, quienes tuvieron, un promedio, de más de seis hijos. La mayoría de los centenarios viven con sus familias, solo dos se hallaban en hogares para ancianos, lo opuesto a lo que se encuentra en otras zonas del mundo.\nSegún lo comentaron las doctoras Isabel Barrientos, Fariday Helo y Kattia Alfaro, uno de los aspectos que más les llamó la atención fue el grado de espiritualidad, optimismo, apoyo familiar y sentido de la vida de esta población centenaria.\nEn relación con los hábitos del sueño se concluyó que, en promedio, dormían ocho horas diarias y muy pocos tomaban algun tipo de medicamento para dormir: solo 7 de los 43 centenarios.\nSu dieta era rica en alimentos tales como: frijoles, maíz, legumbres, animales de corral, productos lácteos (queso cuajada), frutas y verduras, muy baja en harinas y carbohidratos, es decir una dieta modesta, pero suficiente. No se encontró ningún persona con un índice de masa corporal en rango de obesidad.\nLa doctora María de los Ángeles Solís explicó que principal afectación fue la parte visual presencia de cataratas operadas, seguida de hipertensión arterial, un porcentaje muy bajo con respecto a lo reportado en población adulta mayor de: diabetes, cáncer, cardiopatía isquémica y enfermedad pulmonar obstructiva crónica. Todas estaban con una pensión del Régimen No Contributivo de Pensiones (RNC) o de las que ofrece la CCSS en el régimen de Invalidez, Vejez y Muerte (IVM).\nEl promedio de medicamentos por centenario fue de menos de uno por persona (0,9), muy bajo con respecto a lo reportado en adultos mayores a nivel literatura mundial\nEl doctor Fabián Madrigal destacó que de los 32 centenarios que se les aplicó la escala de depresión geriátrica, específicamente, en la pregunta que evalúa la satisfaccion de su vida, 30 respondieron estar satisfechos y solamente un participante tenía un puntaje de diagnóstico de depresión, lo cual refleja un alto porcentaje de satisfacción de su estado de vida actual.\nCon base en las pruebas realizadas, los hombres presentaban mejor funcionalidad que las mujeres.\nEl promedio de la glicemia fue de 84 mg/dl, la HbAc fue de 5,5%, hemoglobina de 12,18 g/dl, creatinina de 1,32 mg/dl y una albumina de 3,04 g/dl., colesterol LDL menor a 100 mg/dl promedio, un nivel de PCR promedio menor a uno.\nElectrocardiograma: el 65 % casos tenia un ritmo normal, se documentó arritmia cardiaca con fibrilación auricular en el 9.3 % de los casos, no se documentaron bloqueos atrio ventriculares completos. 20% normales. Solo se detectaron 2 casos con anemias\nTags :\nadultos mayores\ncaja\ncentenarios\nespiritualidad\nlongevidad\nnicoya\nsalud",
    "tags": [
        "adultos mayores",
        "caja",
        "centenarios",
        "espiritualidad",
        "longevidad",
        "nicoya",
        "salud"
    ]
}